afew/DBACL.py
afew/Database.py
afew/FilterRegistry.py
afew/MailMover.py
afew/NotmuchSettings.py
afew/Settings.py
afew/__init__.py
afew/commands.py
afew/configparser.py
afew/files.py
afew/main.py
afew/utils.py
afew/defaults/afew.config
afew/filters/ArchiveSentMailsFilter.py
afew/filters/BaseFilter.py
afew/filters/ClassifyingFilter.py
afew/filters/FolderNameFilter.py
afew/filters/HeaderMatchingFilter.py
afew/filters/InboxFilter.py
afew/filters/KillThreadsFilter.py
afew/filters/ListMailsFilter.py
afew/filters/SentMailsFilter.py
afew/filters/SpamFilter.py
afew/filters/__init__.py
afew/tests/__init__.py
afew/tests/test_settings.py
afew-1.0.0.dist-info/DESCRIPTION.rst
afew-1.0.0.dist-info/METADATA
afew-1.0.0.dist-info/RECORD
afew-1.0.0.dist-info/WHEEL
afew-1.0.0.dist-info/entry_points.txt
afew-1.0.0.dist-info/metadata.json
afew-1.0.0.dist-info/top_level.txt
