Metadata-Version: 2.0
Name: afew
Version: 1.0.0
Summary: UNKNOWN
Home-page: UNKNOWN
Author: UNKNOWN
Author-email: UNKNOWN
License: UNKNOWN
Platform: UNKNOWN
Provides: afew
Requires-Dist: chardet
Requires-Dist: notmuch
